_version.py
eindir-0.1.0.dist-info/METADATA
eindir-0.1.0.dist-info/WHEEL
eindir-0.1.0.dist-info/licenses/LICENSE
eindir/__init__.py
eindir/core/__init__.py
eindir/core/components.py
eindir/core/exceptions.py
eindir/viz/__init__.py
eindir/viz/viz2d.py
eindir-0.1.0.dist-info/RECORD
